boto_formatter/__init__.py
boto_formatter/boto_magic_formatter.py
boto_formatter/core_formatter.py
boto_formatter/service_formatter.py
boto_formatter/json_util/__init__.py
boto_formatter/json_util/json_util.py
boto_formatter/service_config_mgr/__init__.py
boto_formatter/service_config_mgr/service_config.py
boto_formatter/service_config_mgr/service_configs/accessanalyzer.json
boto_formatter/service_config_mgr/service_configs/account.json
boto_formatter/service_config_mgr/service_configs/acm.json
boto_formatter/service_config_mgr/service_configs/amp.json
boto_formatter/service_config_mgr/service_configs/apigateway.json
boto_formatter/service_config_mgr/service_configs/budgets.json
boto_formatter/service_config_mgr/service_configs/cleanrooms.json
boto_formatter/service_config_mgr/service_configs/cloudformation.json
boto_formatter/service_config_mgr/service_configs/cloudfront.json
boto_formatter/service_config_mgr/service_configs/cloudtrail.json
boto_formatter/service_config_mgr/service_configs/cloudwatch.json
boto_formatter/service_config_mgr/service_configs/codecommit.json
boto_formatter/service_config_mgr/service_configs/dynamodb.json
boto_formatter/service_config_mgr/service_configs/ec2.json
boto_formatter/service_config_mgr/service_configs/ecs.json
boto_formatter/service_config_mgr/service_configs/efs.json
boto_formatter/service_config_mgr/service_configs/eks.json
boto_formatter/service_config_mgr/service_configs/elasticache.json
boto_formatter/service_config_mgr/service_configs/elbv2.json
boto_formatter/service_config_mgr/service_configs/emr-serverless.json
boto_formatter/service_config_mgr/service_configs/emr.json
boto_formatter/service_config_mgr/service_configs/iam.json
boto_formatter/service_config_mgr/service_configs/kms.json
boto_formatter/service_config_mgr/service_configs/lambda.json
boto_formatter/service_config_mgr/service_configs/organizations.json
boto_formatter/service_config_mgr/service_configs/rds.json
boto_formatter-2.0.0.dist-info/LICENSE
boto_formatter-2.0.0.dist-info/METADATA
boto_formatter-2.0.0.dist-info/WHEEL
boto_formatter-2.0.0.dist-info/top_level.txt
boto_formatter-2.0.0.dist-info/RECORD
