Metadata-Version: 2.1
Name: boto_formatter
Version: 2.0.0
Summary: boto3 response formatter
Author-email: Abhijit Rajeshirke <rajeabh@amazon.com>
Project-URL: Homepage, https://github.com/awslabs/boto-formatter
Project-URL: Bug Tracker, https://github.com/awslabs/boto-formatter/issues
Classifier: Programming Language :: Python :: 3
Classifier: License :: OSI Approved :: MIT License
Classifier: Operating System :: OS Independent
Requires-Python: >=3.7
License-File: LICENSE
